increaseviews/__init__.py
increaseviews/increaseviews.py
increaseviews-0.0.2.dist-info/METADATA
increaseviews-0.0.2.dist-info/WHEEL
increaseviews-0.0.2.dist-info/top_level.txt
increaseviews-0.0.2.dist-info/RECORD
