Metadata-Version: 2.1
Name: increaseviews
Version: 0.0.2
Summary: A package to increase youtube views of any channel
Home-page: UNKNOWN
Author: CodeWithNazal (Nazal Ahmed)
Author-email: <ziluzephyr@gmail.com>
License: UNKNOWN
Keywords: python,video,youtube,views,automation
Platform: UNKNOWN
Classifier: Development Status :: 5 - Production/Stable
Classifier: Intended Audience :: Developers
Classifier: Programming Language :: Python :: 3
Classifier: Operating System :: Unix
Classifier: Operating System :: MacOS :: MacOS X
Classifier: Operating System :: Microsoft :: Windows
Requires-Dist: selenium
